doit4u/__init__.py
doit4u/doit4u.py
doit4u-0.1.0.dist-info/LICENSE
doit4u-0.1.0.dist-info/METADATA
doit4u-0.1.0.dist-info/WHEEL
doit4u-0.1.0.dist-info/top_level.txt
doit4u-0.1.0.dist-info/RECORD
