Metadata-Version: 2.1
Name: doit4u
Version: 0.1.0
Summary: A natural language hybrid Python programming framework based on OpenAI API.
Home-page: https://github.com/ChuanyuXue/doit4u
Author: Chuanyu Xue
Author-email: skewcy@gmail.com
Classifier: Development Status :: 3 - Alpha
Classifier: Intended Audience :: Developers
Classifier: License :: OSI Approved :: MIT License
Classifier: Programming Language :: Python :: 3
Classifier: Programming Language :: Python :: 3.6
Classifier: Programming Language :: Python :: 3.7
Classifier: Programming Language :: Python :: 3.8
Classifier: Programming Language :: Python :: 3.9
Requires-Python: >=3.6
License-File: LICENSE
Requires-Dist: openai
